{
  "tickets": [
    {
      "ticket_id": "TKT-001",
      "subject": "Incorrect charge on my account",
      "body": "Hi, I noticed I was charged $49.99 on March 15th but my plan is $29.99/month. I have not upgraded anything. Please investigate and issue a correction immediately.",
      "sender_email": "john.doe@example.com",
      "timestamp": "2025-03-16T09:14:00Z",
      "gt_category": "billing",
      "gt_priority": "high",
      "gt_team": "billing_team",
      "response_keywords": [
        "charge",
        "investigate",
        "refund",
        "apologize",
        "account"
      ]
    },
    {
      "ticket_id": "TKT-002",
      "subject": "Need invoice for last 3 months",
      "body": "Hello, I am preparing our quarterly expense report and need PDF invoices for January, February, and March. Could you send them to finance@acmecorp.com?",
      "sender_email": "mary.finance@acmecorp.com",
      "timestamp": "2025-03-20T11:00:00Z",
      "gt_category": "billing",
      "gt_priority": "medium",
      "gt_team": "billing_team",
      "response_keywords": [
        "invoice",
        "send",
        "email",
        "attach"
      ]
    },
    {
      "ticket_id": "TKT-003",
      "subject": "Upgrade to annual plan billing question",
      "body": "I would like to switch from monthly $29.99 to annual billing. Will I be charged a prorated amount for the remaining days of this month?",
      "sender_email": "sam.user@gmail.com",
      "timestamp": "2025-03-21T14:30:00Z",
      "gt_category": "billing",
      "gt_priority": "low",
      "gt_team": "billing_team",
      "response_keywords": [
        "prorated",
        "annual",
        "billing",
        "upgrade"
      ]
    },
    {
      "ticket_id": "TKT-023",
      "subject": "Wrong plan shown after upgrade",
      "body": "I upgraded from Basic to Pro yesterday but my dashboard still shows Basic features. The payment went through, I have the receipt.",
      "sender_email": "upgraded@user.net",
      "timestamp": "2025-03-22T14:00:00Z",
      "gt_category": "billing",
      "gt_priority": "high",
      "gt_team": "billing_team",
      "response_keywords": [
        "upgrade",
        "plan",
        "sync",
        "fix",
        "Pro"
      ]
    },
    {
      "ticket_id": "TKT-024",
      "subject": "Request for custom enterprise pricing",
      "body": "We have 500 plus users and are evaluating your Enterprise plan. Can someone from sales contact me to discuss volume pricing?",
      "sender_email": "vp.ops@largeenterprise.com",
      "timestamp": "2025-03-19T08:00:00Z",
      "gt_category": "billing",
      "gt_priority": "high",
      "gt_team": "customer_success",
      "response_keywords": [
        "enterprise",
        "sales",
        "contact",
        "volume",
        "discuss"
      ]
    },
    {
      "ticket_id": "TKT-004",
      "subject": "Cannot log in 500 error",
      "body": "Every time I try to log in I get a 500 Internal Server Error. This started about an hour ago. I have cleared my cache and tried a different browser. My account is alice@startup.io.",
      "sender_email": "alice@startup.io",
      "timestamp": "2025-03-22T08:05:00Z",
      "gt_category": "technical",
      "gt_priority": "critical",
      "gt_team": "tech_support",
      "response_keywords": [
        "500",
        "investigate",
        "engineers",
        "status",
        "sorry"
      ]
    },
    {
      "ticket_id": "TKT-005",
      "subject": "API rate limit 429 errors",
      "body": "Our integration has been hitting 429 Too Many Requests since yesterday. We send about 800 requests per minute but our plan allows 1000 per minute. This is blocking production.",
      "sender_email": "devops@bigcorp.com",
      "timestamp": "2025-03-22T10:20:00Z",
      "gt_category": "technical",
      "gt_priority": "critical",
      "gt_team": "tech_support",
      "response_keywords": [
        "rate limit",
        "investigate",
        "engineering",
        "apologize"
      ]
    },
    {
      "ticket_id": "TKT-006",
      "subject": "CSV export is missing some columns",
      "body": "When I export my data to CSV the columns created_at and tags are missing from the file. This has been happening since last Tuesday.",
      "sender_email": "user123@domain.com",
      "timestamp": "2025-03-19T16:45:00Z",
      "gt_category": "technical",
      "gt_priority": "medium",
      "gt_team": "tech_support",
      "response_keywords": [
        "export",
        "columns",
        "bug",
        "fix"
      ]
    },
    {
      "ticket_id": "TKT-007",
      "subject": "Suspected security breach unauthorized logins",
      "body": "I received email alerts for 3 logins from IP 203.0.113.42 in Brazil that were NOT me. I am in Germany and my account has sensitive data. Please lock my account immediately and investigate.",
      "sender_email": "ernst.m@germancorp.de",
      "timestamp": "2025-03-23T02:11:00Z",
      "gt_category": "technical",
      "gt_priority": "critical",
      "gt_team": "tech_support",
      "response_keywords": [
        "security",
        "lock",
        "account",
        "investigate",
        "unauthorized"
      ]
    },
    {
      "ticket_id": "TKT-008",
      "subject": "How to integrate with Zapier",
      "body": "I am trying to set up a Zap that triggers when a new record is created in your system. I have followed the docs but the trigger does not fire. Any step by step guidance?",
      "sender_email": "zap.user@creative.agency",
      "timestamp": "2025-03-18T13:00:00Z",
      "gt_category": "technical",
      "gt_priority": "low",
      "gt_team": "tech_support",
      "response_keywords": [
        "zapier",
        "integration",
        "webhook",
        "guide",
        "steps"
      ]
    },
    {
      "ticket_id": "TKT-018",
      "subject": "Account locked after too many failed logins",
      "body": "I forgot my password and now my account is locked after 5 attempts. How do I unlock it? I have already tried the forgot password link.",
      "sender_email": "locked.out@personal.net",
      "timestamp": "2025-03-22T07:45:00Z",
      "gt_category": "technical",
      "gt_priority": "high",
      "gt_team": "tech_support",
      "response_keywords": [
        "unlock",
        "account",
        "password",
        "reset",
        "verify"
      ]
    },
    {
      "ticket_id": "TKT-019",
      "subject": "Bulk import failing with parse error",
      "body": "I am trying to import 5000 records via your CSV bulk import tool and getting Parse error on row 1423. The CSV was exported from Salesforce. This is urgent, migration deadline is tomorrow.",
      "sender_email": "migration@bigclient.com",
      "timestamp": "2025-03-23T16:10:00Z",
      "gt_category": "technical",
      "gt_priority": "critical",
      "gt_team": "tech_support",
      "response_keywords": [
        "parse error",
        "import",
        "CSV",
        "urgent",
        "engineer"
      ]
    },
    {
      "ticket_id": "TKT-022",
      "subject": "Integration with Slack not working",
      "body": "Our Slack notifications stopped working 2 days ago. I have re-authenticated the integration but still no messages are sent. Workspace is acme-team.slack.com",
      "sender_email": "it@acmeteam.com",
      "timestamp": "2025-03-20T09:00:00Z",
      "gt_category": "technical",
      "gt_priority": "high",
      "gt_team": "tech_support",
      "response_keywords": [
        "Slack",
        "integration",
        "logs",
        "fix"
      ]
    },
    {
      "ticket_id": "TKT-025",
      "subject": "Service completely down revenue impact",
      "body": "URGENT. All our users are unable to access the platform. We have been down for 45 minutes. This is causing direct revenue loss estimated at 10000 dollars per hour. Need immediate escalation to engineering.",
      "sender_email": "cto@criticalclient.com",
      "timestamp": "2025-03-23T13:00:00Z",
      "gt_category": "technical",
      "gt_priority": "critical",
      "gt_team": "tech_support",
      "response_keywords": [
        "outage",
        "engineering",
        "escalate",
        "update",
        "priority"
      ]
    },
    {
      "ticket_id": "TKT-009",
      "subject": "Requesting full refund unused subscription",
      "body": "I signed up by mistake last week and have not used the service at all. I would like a full refund of 149.99 dollars under your 30 day money back guarantee.",
      "sender_email": "newuser@hotmail.com",
      "timestamp": "2025-03-21T18:55:00Z",
      "gt_category": "refund",
      "gt_priority": "high",
      "gt_team": "billing_team",
      "response_keywords": [
        "refund",
        "guarantee",
        "process",
        "business days"
      ]
    },
    {
      "ticket_id": "TKT-010",
      "subject": "Partial refund for downtime",
      "body": "Your system was down for 6 hours on March 10th incident INC-2203. Per your SLA we are entitled to a service credit. Please apply this to our next invoice.",
      "sender_email": "ops@enterprise.com",
      "timestamp": "2025-03-15T09:30:00Z",
      "gt_category": "refund",
      "gt_priority": "medium",
      "gt_team": "billing_team",
      "response_keywords": [
        "SLA",
        "credit",
        "incident",
        "apply",
        "invoice"
      ]
    },
    {
      "ticket_id": "TKT-020",
      "subject": "Duplicate charges please refund one",
      "body": "I was charged twice in March, once on the 1st and again on the 3rd, both for 29.99 dollars. Only one should have gone through. Transactions TXN-9912 and TXN-9945.",
      "sender_email": "double.charged@example.com",
      "timestamp": "2025-03-10T12:00:00Z",
      "gt_category": "refund",
      "gt_priority": "high",
      "gt_team": "billing_team",
      "response_keywords": [
        "duplicate",
        "refund",
        "transaction",
        "apologize",
        "process"
      ]
    },
    {
      "ticket_id": "TKT-011",
      "subject": "Absolutely unacceptable service escalation required",
      "body": "This is the THIRD time I am writing about the same issue and nobody has resolved it. My data has been corrupted for 2 weeks, your support keeps closing tickets without fixing anything. I am considering legal action.",
      "sender_email": "angry.client@lawfirm.com",
      "timestamp": "2025-03-22T11:30:00Z",
      "gt_category": "complaint",
      "gt_priority": "critical",
      "gt_team": "management",
      "response_keywords": [
        "apologize",
        "escalate",
        "manager",
        "priority",
        "resolve"
      ]
    },
    {
      "ticket_id": "TKT-012",
      "subject": "Misleading pricing on your website",
      "body": "Your homepage says starting at 9 dollars per month but when I checked out the actual minimum was 29 dollars per month. This is false advertising.",
      "sender_email": "concerned@gmail.com",
      "timestamp": "2025-03-20T15:00:00Z",
      "gt_category": "complaint",
      "gt_priority": "medium",
      "gt_team": "management",
      "response_keywords": [
        "pricing",
        "apologize",
        "clarify",
        "plan",
        "update"
      ]
    },
    {
      "ticket_id": "TKT-013",
      "subject": "Support agent was rude",
      "body": "The agent I spoke with on ticket 4521 was dismissive and cut me off multiple times. I have been a customer for 3 years and I expect better.",
      "sender_email": "loyal.customer@yahoo.com",
      "timestamp": "2025-03-19T10:15:00Z",
      "gt_category": "complaint",
      "gt_priority": "medium",
      "gt_team": "management",
      "response_keywords": [
        "apologize",
        "feedback",
        "review",
        "improve",
        "valued"
      ]
    },
    {
      "ticket_id": "TKT-014",
      "subject": "How do I add team members",
      "body": "We are growing and I want to invite 5 colleagues to our workspace. Where do I find the team management settings?",
      "sender_email": "manager@startup.io",
      "timestamp": "2025-03-18T14:00:00Z",
      "gt_category": "general",
      "gt_priority": "low",
      "gt_team": "general_support",
      "response_keywords": [
        "settings",
        "invite",
        "team",
        "members",
        "steps"
      ]
    },
    {
      "ticket_id": "TKT-015",
      "subject": "What are your data retention policies",
      "body": "We are doing a GDPR compliance audit. Could you share your data retention policy and DPA Data Processing Agreement?",
      "sender_email": "dpo@eucompany.eu",
      "timestamp": "2025-03-21T09:00:00Z",
      "gt_category": "general",
      "gt_priority": "medium",
      "gt_team": "general_support",
      "response_keywords": [
        "GDPR",
        "retention",
        "DPA",
        "privacy",
        "policy"
      ]
    },
    {
      "ticket_id": "TKT-016",
      "subject": "Cancel my subscription",
      "body": "Please cancel my subscription effective end of this billing period. I am switching to a competitor. No need to try to retain me.",
      "sender_email": "leaving.user@domain.com",
      "timestamp": "2025-03-20T17:30:00Z",
      "gt_category": "general",
      "gt_priority": "medium",
      "gt_team": "customer_success",
      "response_keywords": [
        "cancel",
        "confirm",
        "billing period",
        "sorry",
        "data export"
      ]
    },
    {
      "ticket_id": "TKT-017",
      "subject": "Feature request dark mode",
      "body": "Any plans for dark mode in the dashboard? It would really help with eye strain during long sessions.",
      "sender_email": "dev.user@techco.com",
      "timestamp": "2025-03-17T20:00:00Z",
      "gt_category": "general",
      "gt_priority": "low",
      "gt_team": "general_support",
      "response_keywords": [
        "feature request",
        "roadmap",
        "noted",
        "team"
      ]
    },
    {
      "ticket_id": "TKT-021",
      "subject": "How to export data before cancelling",
      "body": "I am planning to cancel next week. How do I export all my data? I want to make sure I do not lose anything.",
      "sender_email": "exiting@user.com",
      "timestamp": "2025-03-21T11:00:00Z",
      "gt_category": "general",
      "gt_priority": "medium",
      "gt_team": "customer_success",
      "response_keywords": [
        "export",
        "data",
        "steps",
        "before",
        "cancel"
      ]
    }
  ],
  "task_mappings": {
    "classify": [
      "TKT-001",
      "TKT-004",
      "TKT-009",
      "TKT-011",
      "TKT-014"
    ],
    "triage": [
      "TKT-002",
      "TKT-005",
      "TKT-007",
      "TKT-010",
      "TKT-012",
      "TKT-016",
      "TKT-019"
    ],
    "resolve": [
      "TKT-003",
      "TKT-006",
      "TKT-008",
      "TKT-011",
      "TKT-020",
      "TKT-022",
      "TKT-025"
    ]
  }
}